{
  "manifestVersion": "3.2",
  "admin": {
    "address": "0x8eBc0a4e43314432fB9a98d8389686e873f045E2",
    "txHash": "0x5232da6091f8c97a9fb5fca0b7f9a2e862a8b04f3d0f890a30795f2cbd83dfd7"
  },
  "proxies": [
    {
      "address": "0x830eC428bd702E220b86072f4d6e16FBEd8435Cb",
      "txHash": "0xa89c1233c2319e6371a9405f27b674196547f33c0584beed8c032637289f9c09",
      "kind": "transparent"
    },
    {
      "address": "0xB09cdB677510C67cf1D3D5fC3A8d66618AD38C21",
      "txHash": "0x5758b91e16589ec065c593cd0bdb527668dbac0b3e598ff3f73ad1eda35ccd6b",
      "kind": "transparent"
    },
    {
      "address": "0xf4060d96C1E5BfAEa69F3E9039ad29B4e333f807",
      "txHash": "0x51d39230e334f01ab2694fc9887758143fd9d2e86ce1d0d4bb39c63cd388660a",
      "kind": "transparent"
    },
    {
      "address": "0x3f204484ABBB0d8E61049574152C4ae0b011d905",
      "txHash": "0x83707f0535d1a39bce94c5638279570f347ae63eab9de62d663fcf823b18b732",
      "kind": "transparent"
    },
    {
      "address": "0x8a50386B66b429B6Bf0AcF070fDFAA5f148BbAc0",
      "txHash": "0x7a3925f4c76714937f5e016ea0fbaf13378ae7964a7934d5247737ade270bb3c",
      "kind": "transparent"
    },
    {
      "address": "0x954647990Ff7B30cA544Be074F747b8204025f6B",
      "txHash": "0x16d5d8a77711923e8e88cf2a601fbe8f691aefa34d9579a552278846100b2a58",
      "kind": "transparent"
    },
    {
      "address": "0x2d1a23202a943fAcB0e2e94f61fdC524EB2572F3",
      "txHash": "0x4b9b3110be82e3e97a20c99131bc5a011a329c18fd15267a3f13061494b78e0a",
      "kind": "transparent"
    },
    {
      "address": "0xCbe20d1F8f4Ba8cd313657426142dEbEF448E91f",
      "txHash": "0x01c0d98cf64c6593c6774f92f5e8c2e17be911825c953845e7e8e2e1d494ac0d",
      "kind": "transparent"
    },
    {
      "address": "0x92F9eB5824211aA291EadDb3755220AC68Ef2BF1",
      "txHash": "0x11fef7ef4f826eff391b2b7d148896d28618595fb12db5949aa037e6e614c483",
      "kind": "transparent"
    },
    {
      "address": "0xAB884556Bd9aF789c52F91AfA428FEA93A43F09D",
      "txHash": "0xe95d7b6cfb295dcda969e095bc18f3978b75f66e1a6f2a00585ebf8b08658508",
      "kind": "transparent"
    },
    {
      "address": "0xA8cD928a8346FB37D8d5D4f4EC867f6c4073dedB",
      "txHash": "0xed66a44c0e79e76e9b8142d1acd2e1f9f37624856e8029861d03bd2d81ad1748",
      "kind": "transparent"
    },
    {
      "address": "0xE29bEcd03CB2e915f0821a9da8DEFECF68f90D64",
      "txHash": "0xb0b607c00d03d29759c966490eabcb3bb26c77c92433615a12ed1a1119e0c0aa",
      "kind": "transparent"
    },
    {
      "address": "0x25aeF2397aCd724D0B448d9c87B7083b33282d59",
      "txHash": "0xaf938a170ca9cc377a08e06f5956384a610fa910a264535f7cc9b32c6122f4cd",
      "kind": "transparent"
    }
  ],
  "impls": {
    "12f84715afcd354fe2d91ac6bd5f2ff3d55150d430cf5d09e69f6ccc6623d82d": {
      "address": "0x0a65598b48fEe01664ac30d5Cc153AbE1AA7a2A7",
      "txHash": "0x1cb38c4099a6aa753343a05ac02af7470e28a698a5ba4d9348dc7ff9998b8640",
      "layout": {
        "solcVersion": "0.8.10",
        "storage": [
          {
            "label": "_initialized",
            "offset": 0,
            "slot": "0",
            "type": "t_uint8",
            "contract": "Initializable",
            "src": "@openzeppelin\\contracts-upgradeable\\proxy\\utils\\Initializable.sol:62",
            "retypedFrom": "bool"
          },
          {
            "label": "_initializing",
            "offset": 1,
            "slot": "0",
            "type": "t_bool",
            "contract": "Initializable",
            "src": "@openzeppelin\\contracts-upgradeable\\proxy\\utils\\Initializable.sol:67"
          },
          {
            "label": "__gap",
            "offset": 0,
            "slot": "1",
            "type": "t_array(t_uint256)50_storage",
            "contract": "ContextUpgradeable",
            "src": "@openzeppelin\\contracts-upgradeable\\utils\\ContextUpgradeable.sol:36"
          },
          {
            "label": "__gap",
            "offset": 0,
            "slot": "51",
            "type": "t_array(t_uint256)50_storage",
            "contract": "ERC165Upgradeable",
            "src": "@openzeppelin\\contracts-upgradeable\\utils\\introspection\\ERC165Upgradeable.sol:41"
          },
          {
            "label": "_balances",
            "offset": 0,
            "slot": "101",
            "type": "t_mapping(t_uint256,t_mapping(t_address,t_uint256))",
            "contract": "ERC1155Upgradeable",
            "src": "@openzeppelin\\contracts-upgradeable\\token\\ERC1155\\ERC1155Upgradeable.sol:25"
          },
          {
            "label": "_operatorApprovals",
            "offset": 0,
            "slot": "102",
            "type": "t_mapping(t_address,t_mapping(t_address,t_bool))",
            "contract": "ERC1155Upgradeable",
            "src": "@openzeppelin\\contracts-upgradeable\\token\\ERC1155\\ERC1155Upgradeable.sol:28"
          },
          {
            "label": "_uri",
            "offset": 0,
            "slot": "103",
            "type": "t_string_storage",
            "contract": "ERC1155Upgradeable",
            "src": "@openzeppelin\\contracts-upgradeable\\token\\ERC1155\\ERC1155Upgradeable.sol:31"
          },
          {
            "label": "__gap",
            "offset": 0,
            "slot": "104",
            "type": "t_array(t_uint256)47_storage",
            "contract": "ERC1155Upgradeable",
            "src": "@openzeppelin\\contracts-upgradeable\\token\\ERC1155\\ERC1155Upgradeable.sol:528"
          },
          {
            "label": "_owner",
            "offset": 0,
            "slot": "151",
            "type": "t_address",
            "contract": "OwnableUpgradeable",
            "src": "@openzeppelin\\contracts-upgradeable\\access\\OwnableUpgradeable.sol:22"
          },
          {
            "label": "__gap",
            "offset": 0,
            "slot": "152",
            "type": "t_array(t_uint256)49_storage",
            "contract": "OwnableUpgradeable",
            "src": "@openzeppelin\\contracts-upgradeable\\access\\OwnableUpgradeable.sol:94"
          },
          {
            "label": "name",
            "offset": 0,
            "slot": "201",
            "type": "t_string_storage",
            "contract": "NFTbadge",
            "src": "contracts\\NFTbadge.sol:11"
          },
          {
            "label": "symbol",
            "offset": 0,
            "slot": "202",
            "type": "t_string_storage",
            "contract": "NFTbadge",
            "src": "contracts\\NFTbadge.sol:12"
          },
          {
            "label": "paused",
            "offset": 0,
            "slot": "203",
            "type": "t_bool",
            "contract": "NFTbadge",
            "src": "contracts\\NFTbadge.sol:13"
          },
          {
            "label": "tokenURI",
            "offset": 0,
            "slot": "204",
            "type": "t_mapping(t_uint256,t_string_storage)",
            "contract": "NFTbadge",
            "src": "contracts\\NFTbadge.sol:15"
          }
        ],
        "types": {
          "t_address": {
            "label": "address",
            "numberOfBytes": "20"
          },
          "t_array(t_uint256)47_storage": {
            "label": "uint256[47]",
            "numberOfBytes": "1504"
          },
          "t_array(t_uint256)49_storage": {
            "label": "uint256[49]",
            "numberOfBytes": "1568"
          },
          "t_array(t_uint256)50_storage": {
            "label": "uint256[50]",
            "numberOfBytes": "1600"
          },
          "t_bool": {
            "label": "bool",
            "numberOfBytes": "1"
          },
          "t_mapping(t_address,t_bool)": {
            "label": "mapping(address => bool)",
            "numberOfBytes": "32"
          },
          "t_mapping(t_address,t_mapping(t_address,t_bool))": {
            "label": "mapping(address => mapping(address => bool))",
            "numberOfBytes": "32"
          },
          "t_mapping(t_address,t_uint256)": {
            "label": "mapping(address => uint256)",
            "numberOfBytes": "32"
          },
          "t_mapping(t_uint256,t_mapping(t_address,t_uint256))": {
            "label": "mapping(uint256 => mapping(address => uint256))",
            "numberOfBytes": "32"
          },
          "t_mapping(t_uint256,t_string_storage)": {
            "label": "mapping(uint256 => string)",
            "numberOfBytes": "32"
          },
          "t_string_storage": {
            "label": "string",
            "numberOfBytes": "32"
          },
          "t_uint256": {
            "label": "uint256",
            "numberOfBytes": "32"
          },
          "t_uint8": {
            "label": "uint8",
            "numberOfBytes": "1"
          }
        }
      }
    },
    "7a358e0cf6787cff3fcc510185eb8deb74ba55c31077eba442af5d68b8a3d2f2": {
      "address": "0xAC26862FFC9C0B45A7a577702a042F2940565C9C",
      "txHash": "0x5a2a264493bb5e0d6afc9dd09a2a8a2d938618feec4307dbd733fdba9a5a015e",
      "layout": {
        "solcVersion": "0.8.10",
        "storage": [
          {
            "label": "_initialized",
            "offset": 0,
            "slot": "0",
            "type": "t_uint8",
            "contract": "Initializable",
            "src": "@openzeppelin\\contracts-upgradeable\\proxy\\utils\\Initializable.sol:62",
            "retypedFrom": "bool"
          },
          {
            "label": "_initializing",
            "offset": 1,
            "slot": "0",
            "type": "t_bool",
            "contract": "Initializable",
            "src": "@openzeppelin\\contracts-upgradeable\\proxy\\utils\\Initializable.sol:67"
          },
          {
            "label": "__gap",
            "offset": 0,
            "slot": "1",
            "type": "t_array(t_uint256)50_storage",
            "contract": "ContextUpgradeable",
            "src": "@openzeppelin\\contracts-upgradeable\\utils\\ContextUpgradeable.sol:36"
          },
          {
            "label": "_owner",
            "offset": 0,
            "slot": "51",
            "type": "t_address",
            "contract": "OwnableUpgradeable",
            "src": "@openzeppelin\\contracts-upgradeable\\access\\OwnableUpgradeable.sol:22"
          },
          {
            "label": "__gap",
            "offset": 0,
            "slot": "52",
            "type": "t_array(t_uint256)49_storage",
            "contract": "OwnableUpgradeable",
            "src": "@openzeppelin\\contracts-upgradeable\\access\\OwnableUpgradeable.sol:94"
          },
          {
            "label": "paused",
            "offset": 0,
            "slot": "101",
            "type": "t_bool",
            "contract": "GameFactory",
            "src": "contracts\\GameFactory.sol:10"
          },
          {
            "label": "games",
            "offset": 0,
            "slot": "102",
            "type": "t_uint256",
            "contract": "GameFactory",
            "src": "contracts\\GameFactory.sol:11"
          }
        ],
        "types": {
          "t_address": {
            "label": "address",
            "numberOfBytes": "20"
          },
          "t_array(t_uint256)49_storage": {
            "label": "uint256[49]",
            "numberOfBytes": "1568"
          },
          "t_array(t_uint256)50_storage": {
            "label": "uint256[50]",
            "numberOfBytes": "1600"
          },
          "t_bool": {
            "label": "bool",
            "numberOfBytes": "1"
          },
          "t_uint256": {
            "label": "uint256",
            "numberOfBytes": "32"
          },
          "t_uint8": {
            "label": "uint8",
            "numberOfBytes": "1"
          }
        }
      }
    },
    "faa929401f66336ca7ddb900612417b79865f55f2578a32a71bc6144f4a05824": {
      "address": "0xB6514930c482026065FF2bcFad42c04312c18F4b",
      "txHash": "0xf34c658764d0049fe41d9acf5b87676f235cee0d6c71f9c86a154b160d964b49",
      "layout": {
        "solcVersion": "0.8.10",
        "storage": [
          {
            "label": "_initialized",
            "offset": 0,
            "slot": "0",
            "type": "t_uint8",
            "contract": "Initializable",
            "src": "@openzeppelin\\contracts-upgradeable\\proxy\\utils\\Initializable.sol:62",
            "retypedFrom": "bool"
          },
          {
            "label": "_initializing",
            "offset": 1,
            "slot": "0",
            "type": "t_bool",
            "contract": "Initializable",
            "src": "@openzeppelin\\contracts-upgradeable\\proxy\\utils\\Initializable.sol:67"
          },
          {
            "label": "__gap",
            "offset": 0,
            "slot": "1",
            "type": "t_array(t_uint256)50_storage",
            "contract": "ContextUpgradeable",
            "src": "@openzeppelin\\contracts-upgradeable\\utils\\ContextUpgradeable.sol:36"
          },
          {
            "label": "__gap",
            "offset": 0,
            "slot": "51",
            "type": "t_array(t_uint256)50_storage",
            "contract": "ERC165Upgradeable",
            "src": "@openzeppelin\\contracts-upgradeable\\utils\\introspection\\ERC165Upgradeable.sol:41"
          },
          {
            "label": "_balances",
            "offset": 0,
            "slot": "101",
            "type": "t_mapping(t_uint256,t_mapping(t_address,t_uint256))",
            "contract": "ERC1155Upgradeable",
            "src": "@openzeppelin\\contracts-upgradeable\\token\\ERC1155\\ERC1155Upgradeable.sol:25"
          },
          {
            "label": "_operatorApprovals",
            "offset": 0,
            "slot": "102",
            "type": "t_mapping(t_address,t_mapping(t_address,t_bool))",
            "contract": "ERC1155Upgradeable",
            "src": "@openzeppelin\\contracts-upgradeable\\token\\ERC1155\\ERC1155Upgradeable.sol:28"
          },
          {
            "label": "_uri",
            "offset": 0,
            "slot": "103",
            "type": "t_string_storage",
            "contract": "ERC1155Upgradeable",
            "src": "@openzeppelin\\contracts-upgradeable\\token\\ERC1155\\ERC1155Upgradeable.sol:31"
          },
          {
            "label": "__gap",
            "offset": 0,
            "slot": "104",
            "type": "t_array(t_uint256)47_storage",
            "contract": "ERC1155Upgradeable",
            "src": "@openzeppelin\\contracts-upgradeable\\token\\ERC1155\\ERC1155Upgradeable.sol:528"
          },
          {
            "label": "_owner",
            "offset": 0,
            "slot": "151",
            "type": "t_address",
            "contract": "OwnableUpgradeable",
            "src": "@openzeppelin\\contracts-upgradeable\\access\\OwnableUpgradeable.sol:22"
          },
          {
            "label": "__gap",
            "offset": 0,
            "slot": "152",
            "type": "t_array(t_uint256)49_storage",
            "contract": "OwnableUpgradeable",
            "src": "@openzeppelin\\contracts-upgradeable\\access\\OwnableUpgradeable.sol:94"
          },
          {
            "label": "name",
            "offset": 0,
            "slot": "201",
            "type": "t_string_storage",
            "contract": "NFTbadge",
            "src": "contracts\\NFTbadge.sol:11"
          },
          {
            "label": "symbol",
            "offset": 0,
            "slot": "202",
            "type": "t_string_storage",
            "contract": "NFTbadge",
            "src": "contracts\\NFTbadge.sol:12"
          },
          {
            "label": "paused",
            "offset": 0,
            "slot": "203",
            "type": "t_bool",
            "contract": "NFTbadge",
            "src": "contracts\\NFTbadge.sol:13"
          },
          {
            "label": "tokenURI",
            "offset": 0,
            "slot": "204",
            "type": "t_mapping(t_uint256,t_string_storage)",
            "contract": "NFTbadge",
            "src": "contracts\\NFTbadge.sol:15"
          }
        ],
        "types": {
          "t_address": {
            "label": "address",
            "numberOfBytes": "20"
          },
          "t_array(t_uint256)47_storage": {
            "label": "uint256[47]",
            "numberOfBytes": "1504"
          },
          "t_array(t_uint256)49_storage": {
            "label": "uint256[49]",
            "numberOfBytes": "1568"
          },
          "t_array(t_uint256)50_storage": {
            "label": "uint256[50]",
            "numberOfBytes": "1600"
          },
          "t_bool": {
            "label": "bool",
            "numberOfBytes": "1"
          },
          "t_mapping(t_address,t_bool)": {
            "label": "mapping(address => bool)",
            "numberOfBytes": "32"
          },
          "t_mapping(t_address,t_mapping(t_address,t_bool))": {
            "label": "mapping(address => mapping(address => bool))",
            "numberOfBytes": "32"
          },
          "t_mapping(t_address,t_uint256)": {
            "label": "mapping(address => uint256)",
            "numberOfBytes": "32"
          },
          "t_mapping(t_uint256,t_mapping(t_address,t_uint256))": {
            "label": "mapping(uint256 => mapping(address => uint256))",
            "numberOfBytes": "32"
          },
          "t_mapping(t_uint256,t_string_storage)": {
            "label": "mapping(uint256 => string)",
            "numberOfBytes": "32"
          },
          "t_string_storage": {
            "label": "string",
            "numberOfBytes": "32"
          },
          "t_uint256": {
            "label": "uint256",
            "numberOfBytes": "32"
          },
          "t_uint8": {
            "label": "uint8",
            "numberOfBytes": "1"
          }
        }
      }
    },
    "b854fbe171bf6fe44120852be95a5121b78026558b704bda4b1922b6736aba6d": {
      "address": "0x53F9308AB409bf5830c26dAD9B9f19b17466329a",
      "txHash": "0xf6269a1435aec2ccb5e1dd2812ed02e9a51491b22d8c0027b1f626cf9b31e925",
      "layout": {
        "solcVersion": "0.8.10",
        "storage": [
          {
            "label": "_initialized",
            "offset": 0,
            "slot": "0",
            "type": "t_uint8",
            "contract": "Initializable",
            "src": "@openzeppelin\\contracts-upgradeable\\proxy\\utils\\Initializable.sol:62",
            "retypedFrom": "bool"
          },
          {
            "label": "_initializing",
            "offset": 1,
            "slot": "0",
            "type": "t_bool",
            "contract": "Initializable",
            "src": "@openzeppelin\\contracts-upgradeable\\proxy\\utils\\Initializable.sol:67"
          },
          {
            "label": "__gap",
            "offset": 0,
            "slot": "1",
            "type": "t_array(t_uint256)50_storage",
            "contract": "ContextUpgradeable",
            "src": "@openzeppelin\\contracts-upgradeable\\utils\\ContextUpgradeable.sol:36"
          },
          {
            "label": "_owner",
            "offset": 0,
            "slot": "51",
            "type": "t_address",
            "contract": "OwnableUpgradeable",
            "src": "@openzeppelin\\contracts-upgradeable\\access\\OwnableUpgradeable.sol:22"
          },
          {
            "label": "__gap",
            "offset": 0,
            "slot": "52",
            "type": "t_array(t_uint256)49_storage",
            "contract": "OwnableUpgradeable",
            "src": "@openzeppelin\\contracts-upgradeable\\access\\OwnableUpgradeable.sol:94"
          },
          {
            "label": "paused",
            "offset": 0,
            "slot": "101",
            "type": "t_bool",
            "contract": "GameFactory",
            "src": "contracts\\GameFactory.sol:10"
          },
          {
            "label": "games",
            "offset": 0,
            "slot": "102",
            "type": "t_uint256",
            "contract": "GameFactory",
            "src": "contracts\\GameFactory.sol:11"
          }
        ],
        "types": {
          "t_address": {
            "label": "address",
            "numberOfBytes": "20"
          },
          "t_array(t_uint256)49_storage": {
            "label": "uint256[49]",
            "numberOfBytes": "1568"
          },
          "t_array(t_uint256)50_storage": {
            "label": "uint256[50]",
            "numberOfBytes": "1600"
          },
          "t_bool": {
            "label": "bool",
            "numberOfBytes": "1"
          },
          "t_uint256": {
            "label": "uint256",
            "numberOfBytes": "32"
          },
          "t_uint8": {
            "label": "uint8",
            "numberOfBytes": "1"
          }
        }
      }
    },
    "c3397cf3180508cea730d348e797c481e157bcd333562e062944309992202940": {
      "address": "0xa9382545dc0a15EA140557403D396acA6067cd45",
      "txHash": "0x808890def7adcd146154f5c221b5610154e2a0c182c3ca5942a4cf8055c0964f",
      "layout": {
        "solcVersion": "0.8.10",
        "storage": [
          {
            "label": "_initialized",
            "offset": 0,
            "slot": "0",
            "type": "t_uint8",
            "contract": "Initializable",
            "src": "@openzeppelin\\contracts-upgradeable\\proxy\\utils\\Initializable.sol:62",
            "retypedFrom": "bool"
          },
          {
            "label": "_initializing",
            "offset": 1,
            "slot": "0",
            "type": "t_bool",
            "contract": "Initializable",
            "src": "@openzeppelin\\contracts-upgradeable\\proxy\\utils\\Initializable.sol:67"
          },
          {
            "label": "__gap",
            "offset": 0,
            "slot": "1",
            "type": "t_array(t_uint256)50_storage",
            "contract": "ContextUpgradeable",
            "src": "@openzeppelin\\contracts-upgradeable\\utils\\ContextUpgradeable.sol:36"
          },
          {
            "label": "__gap",
            "offset": 0,
            "slot": "51",
            "type": "t_array(t_uint256)50_storage",
            "contract": "ERC165Upgradeable",
            "src": "@openzeppelin\\contracts-upgradeable\\utils\\introspection\\ERC165Upgradeable.sol:41"
          },
          {
            "label": "_balances",
            "offset": 0,
            "slot": "101",
            "type": "t_mapping(t_uint256,t_mapping(t_address,t_uint256))",
            "contract": "ERC1155Upgradeable",
            "src": "@openzeppelin\\contracts-upgradeable\\token\\ERC1155\\ERC1155Upgradeable.sol:25"
          },
          {
            "label": "_operatorApprovals",
            "offset": 0,
            "slot": "102",
            "type": "t_mapping(t_address,t_mapping(t_address,t_bool))",
            "contract": "ERC1155Upgradeable",
            "src": "@openzeppelin\\contracts-upgradeable\\token\\ERC1155\\ERC1155Upgradeable.sol:28"
          },
          {
            "label": "_uri",
            "offset": 0,
            "slot": "103",
            "type": "t_string_storage",
            "contract": "ERC1155Upgradeable",
            "src": "@openzeppelin\\contracts-upgradeable\\token\\ERC1155\\ERC1155Upgradeable.sol:31"
          },
          {
            "label": "__gap",
            "offset": 0,
            "slot": "104",
            "type": "t_array(t_uint256)47_storage",
            "contract": "ERC1155Upgradeable",
            "src": "@openzeppelin\\contracts-upgradeable\\token\\ERC1155\\ERC1155Upgradeable.sol:528"
          },
          {
            "label": "_owner",
            "offset": 0,
            "slot": "151",
            "type": "t_address",
            "contract": "OwnableUpgradeable",
            "src": "@openzeppelin\\contracts-upgradeable\\access\\OwnableUpgradeable.sol:22"
          },
          {
            "label": "__gap",
            "offset": 0,
            "slot": "152",
            "type": "t_array(t_uint256)49_storage",
            "contract": "OwnableUpgradeable",
            "src": "@openzeppelin\\contracts-upgradeable\\access\\OwnableUpgradeable.sol:94"
          },
          {
            "label": "name",
            "offset": 0,
            "slot": "201",
            "type": "t_string_storage",
            "contract": "NFTbadge",
            "src": "contracts\\NFTbadge.sol:11"
          },
          {
            "label": "symbol",
            "offset": 0,
            "slot": "202",
            "type": "t_string_storage",
            "contract": "NFTbadge",
            "src": "contracts\\NFTbadge.sol:12"
          },
          {
            "label": "paused",
            "offset": 0,
            "slot": "203",
            "type": "t_bool",
            "contract": "NFTbadge",
            "src": "contracts\\NFTbadge.sol:13"
          },
          {
            "label": "tokenURI",
            "offset": 0,
            "slot": "204",
            "type": "t_mapping(t_uint256,t_string_storage)",
            "contract": "NFTbadge",
            "src": "contracts\\NFTbadge.sol:15"
          }
        ],
        "types": {
          "t_address": {
            "label": "address",
            "numberOfBytes": "20"
          },
          "t_array(t_uint256)47_storage": {
            "label": "uint256[47]",
            "numberOfBytes": "1504"
          },
          "t_array(t_uint256)49_storage": {
            "label": "uint256[49]",
            "numberOfBytes": "1568"
          },
          "t_array(t_uint256)50_storage": {
            "label": "uint256[50]",
            "numberOfBytes": "1600"
          },
          "t_bool": {
            "label": "bool",
            "numberOfBytes": "1"
          },
          "t_mapping(t_address,t_bool)": {
            "label": "mapping(address => bool)",
            "numberOfBytes": "32"
          },
          "t_mapping(t_address,t_mapping(t_address,t_bool))": {
            "label": "mapping(address => mapping(address => bool))",
            "numberOfBytes": "32"
          },
          "t_mapping(t_address,t_uint256)": {
            "label": "mapping(address => uint256)",
            "numberOfBytes": "32"
          },
          "t_mapping(t_uint256,t_mapping(t_address,t_uint256))": {
            "label": "mapping(uint256 => mapping(address => uint256))",
            "numberOfBytes": "32"
          },
          "t_mapping(t_uint256,t_string_storage)": {
            "label": "mapping(uint256 => string)",
            "numberOfBytes": "32"
          },
          "t_string_storage": {
            "label": "string",
            "numberOfBytes": "32"
          },
          "t_uint256": {
            "label": "uint256",
            "numberOfBytes": "32"
          },
          "t_uint8": {
            "label": "uint8",
            "numberOfBytes": "1"
          }
        }
      }
    },
    "79d253a547229c3cd6a59a6170e363da8fdf7152836a2609cc77562f4c7e1fbf": {
      "address": "0x33816190eA77Ad8701DC303764Fb81fFe1b38977",
      "txHash": "0xed06a64935e3f99d47e962757fa92f1cdd980c26b7561ef4bca6b07213f6d90c",
      "layout": {
        "solcVersion": "0.8.10",
        "storage": [
          {
            "label": "_initialized",
            "offset": 0,
            "slot": "0",
            "type": "t_uint8",
            "contract": "Initializable",
            "src": "@openzeppelin\\contracts-upgradeable\\proxy\\utils\\Initializable.sol:62",
            "retypedFrom": "bool"
          },
          {
            "label": "_initializing",
            "offset": 1,
            "slot": "0",
            "type": "t_bool",
            "contract": "Initializable",
            "src": "@openzeppelin\\contracts-upgradeable\\proxy\\utils\\Initializable.sol:67"
          },
          {
            "label": "__gap",
            "offset": 0,
            "slot": "1",
            "type": "t_array(t_uint256)50_storage",
            "contract": "ContextUpgradeable",
            "src": "@openzeppelin\\contracts-upgradeable\\utils\\ContextUpgradeable.sol:36"
          },
          {
            "label": "__gap",
            "offset": 0,
            "slot": "51",
            "type": "t_array(t_uint256)50_storage",
            "contract": "ERC165Upgradeable",
            "src": "@openzeppelin\\contracts-upgradeable\\utils\\introspection\\ERC165Upgradeable.sol:41"
          },
          {
            "label": "_balances",
            "offset": 0,
            "slot": "101",
            "type": "t_mapping(t_uint256,t_mapping(t_address,t_uint256))",
            "contract": "ERC1155Upgradeable",
            "src": "@openzeppelin\\contracts-upgradeable\\token\\ERC1155\\ERC1155Upgradeable.sol:25"
          },
          {
            "label": "_operatorApprovals",
            "offset": 0,
            "slot": "102",
            "type": "t_mapping(t_address,t_mapping(t_address,t_bool))",
            "contract": "ERC1155Upgradeable",
            "src": "@openzeppelin\\contracts-upgradeable\\token\\ERC1155\\ERC1155Upgradeable.sol:28"
          },
          {
            "label": "_uri",
            "offset": 0,
            "slot": "103",
            "type": "t_string_storage",
            "contract": "ERC1155Upgradeable",
            "src": "@openzeppelin\\contracts-upgradeable\\token\\ERC1155\\ERC1155Upgradeable.sol:31"
          },
          {
            "label": "__gap",
            "offset": 0,
            "slot": "104",
            "type": "t_array(t_uint256)47_storage",
            "contract": "ERC1155Upgradeable",
            "src": "@openzeppelin\\contracts-upgradeable\\token\\ERC1155\\ERC1155Upgradeable.sol:528"
          },
          {
            "label": "_owner",
            "offset": 0,
            "slot": "151",
            "type": "t_address",
            "contract": "OwnableUpgradeable",
            "src": "@openzeppelin\\contracts-upgradeable\\access\\OwnableUpgradeable.sol:22"
          },
          {
            "label": "__gap",
            "offset": 0,
            "slot": "152",
            "type": "t_array(t_uint256)49_storage",
            "contract": "OwnableUpgradeable",
            "src": "@openzeppelin\\contracts-upgradeable\\access\\OwnableUpgradeable.sol:94"
          },
          {
            "label": "name",
            "offset": 0,
            "slot": "201",
            "type": "t_string_storage",
            "contract": "NFTbadge",
            "src": "contracts\\NFTbadge.sol:11"
          },
          {
            "label": "symbol",
            "offset": 0,
            "slot": "202",
            "type": "t_string_storage",
            "contract": "NFTbadge",
            "src": "contracts\\NFTbadge.sol:12"
          },
          {
            "label": "paused",
            "offset": 0,
            "slot": "203",
            "type": "t_bool",
            "contract": "NFTbadge",
            "src": "contracts\\NFTbadge.sol:13"
          },
          {
            "label": "tokenURI",
            "offset": 0,
            "slot": "204",
            "type": "t_mapping(t_uint256,t_string_storage)",
            "contract": "NFTbadge",
            "src": "contracts\\NFTbadge.sol:15"
          }
        ],
        "types": {
          "t_address": {
            "label": "address",
            "numberOfBytes": "20"
          },
          "t_array(t_uint256)47_storage": {
            "label": "uint256[47]",
            "numberOfBytes": "1504"
          },
          "t_array(t_uint256)49_storage": {
            "label": "uint256[49]",
            "numberOfBytes": "1568"
          },
          "t_array(t_uint256)50_storage": {
            "label": "uint256[50]",
            "numberOfBytes": "1600"
          },
          "t_bool": {
            "label": "bool",
            "numberOfBytes": "1"
          },
          "t_mapping(t_address,t_bool)": {
            "label": "mapping(address => bool)",
            "numberOfBytes": "32"
          },
          "t_mapping(t_address,t_mapping(t_address,t_bool))": {
            "label": "mapping(address => mapping(address => bool))",
            "numberOfBytes": "32"
          },
          "t_mapping(t_address,t_uint256)": {
            "label": "mapping(address => uint256)",
            "numberOfBytes": "32"
          },
          "t_mapping(t_uint256,t_mapping(t_address,t_uint256))": {
            "label": "mapping(uint256 => mapping(address => uint256))",
            "numberOfBytes": "32"
          },
          "t_mapping(t_uint256,t_string_storage)": {
            "label": "mapping(uint256 => string)",
            "numberOfBytes": "32"
          },
          "t_string_storage": {
            "label": "string",
            "numberOfBytes": "32"
          },
          "t_uint256": {
            "label": "uint256",
            "numberOfBytes": "32"
          },
          "t_uint8": {
            "label": "uint8",
            "numberOfBytes": "1"
          }
        }
      }
    }
  }
}
